cerebralcortex/__init__.py
cerebralcortex/kernel.py
cerebralcortex/version.py
cerebralcortex/algorithms/__init__.py
cerebralcortex/algorithms/bluetooth/__init__.py
cerebralcortex/algorithms/bluetooth/encounter.py
cerebralcortex/algorithms/ecg/__init__.py
cerebralcortex/algorithms/ecg/autosense_data_quality.py
cerebralcortex/algorithms/ecg/autosense_rr_interval.py
cerebralcortex/algorithms/ecg/hrv_features.py
cerebralcortex/algorithms/ema/__init__.py
cerebralcortex/algorithms/ema/ema_random_features.py
cerebralcortex/algorithms/ema/features.py
cerebralcortex/algorithms/glucose/__init__.py
cerebralcortex/algorithms/glucose/glucose_variability_metrics.py
cerebralcortex/algorithms/gps/__init__.py
cerebralcortex/algorithms/gps/clustering.py
cerebralcortex/algorithms/raw_byte_decode/__init__.py
cerebralcortex/algorithms/raw_byte_decode/motionsenseHRV.py
cerebralcortex/algorithms/rr_intervals/__init__.py
cerebralcortex/algorithms/rr_intervals/rr_interval_feature_extraction.py
cerebralcortex/algorithms/signal_processing/__init__.py
cerebralcortex/algorithms/signal_processing/features.py
cerebralcortex/algorithms/stats/__init__.py
cerebralcortex/algorithms/stats/features.py
cerebralcortex/algorithms/stress_prediction/__init__.py
cerebralcortex/algorithms/stress_prediction/ecg_stress.py
cerebralcortex/algorithms/stress_prediction/stress_episodes.py
cerebralcortex/algorithms/stress_prediction/stress_imputation.py
cerebralcortex/algorithms/stress_prediction/stress_prediction.py
cerebralcortex/algorithms/utils/__init__.py
cerebralcortex/algorithms/utils/feature_normalization.py
cerebralcortex/algorithms/utils/mprov_helper.py
cerebralcortex/algorithms/utils/util.py
cerebralcortex/algorithms/visualization/__init__.py
cerebralcortex/algorithms/visualization/visualization.py
cerebralcortex/core/__init__.py
cerebralcortex/core/config_manager/__init__.py
cerebralcortex/core/config_manager/config.py
cerebralcortex/core/config_manager/config_handler.py
cerebralcortex_kernel-3.3.16.dist-info/LICENSE
cerebralcortex_kernel-3.3.16.dist-info/METADATA
cerebralcortex_kernel-3.3.16.dist-info/WHEEL
cerebralcortex_kernel-3.3.16.dist-info/entry_points.txt
cerebralcortex_kernel-3.3.16.dist-info/top_level.txt
cerebralcortex_kernel-3.3.16.dist-info/RECORD
