Metadata-Version: 2.1
Name: cerebralcortex-kernel
Version: 3.3.16
Summary: Backend data analytics platform for MD2K software
Home-page: https://github.com/MD2Korg/CerebralCortex-Kernel/
Author: MD2K.org
Author-email: dev@md2k.org
License: BSD2
Keywords: mHealth machine-learning data-analysis
Platform: UNKNOWN
Classifier: Development Status :: 5 - Production/Stable
Classifier: Intended Audience :: Healthcare Industry
Classifier: Intended Audience :: Science/Research
Classifier: License :: OSI Approved :: BSD License
Classifier: Natural Language :: English
Classifier: Programming Language :: Python :: 3
Classifier: Topic :: Scientific/Engineering :: Information Analysis
Classifier: Topic :: System :: Distributed Computing
Requires-Dist: wheel
Requires-Dist: pytz
Requires-Dist: PyYAML (>=5.4.1)
Requires-Dist: SQLAlchemy-Utils (==0.37.8)
Requires-Dist: influxdb (==5.3.1)
Requires-Dist: pyarrow (==4.0.1)
Requires-Dist: hdfs3 (==0.3.1)
Requires-Dist: pyspark (==3.1.2)
Requires-Dist: msgpack (==1.0.2)
Requires-Dist: PyJWT (==2.1.0)
Requires-Dist: pandas (==1.1.5)
Requires-Dist: plotly (==5.1.0)
Requires-Dist: datascience (==0.17.0)
Requires-Dist: matplotlib
Requires-Dist: cufflinks (==0.17.3)
Requires-Dist: sqlalchemy (==1.3.24)
Requires-Dist: pennprov (==2.2.9)
Requires-Dist: shapely
Requires-Dist: numpy
Requires-Dist: geopy
Requires-Dist: py-ecg-detectors
Requires-Dist: scikit-learn (==0.22.2.post1)
Requires-Dist: scipy
